mcast_tester/__init__.py
mcast_tester/helpfile.txt
mcast_tester/mcast_reflector.py
mcast_tester/mcast_tester.py
mcast_tester-0.2.dev3.data/data/helpfile.txt
mcast_tester-0.2.dev3.dist-info/DESCRIPTION.rst
mcast_tester-0.2.dev3.dist-info/METADATA
mcast_tester-0.2.dev3.dist-info/RECORD
mcast_tester-0.2.dev3.dist-info/WHEEL
mcast_tester-0.2.dev3.dist-info/metadata.json
mcast_tester-0.2.dev3.dist-info/top_level.txt
