Metadata-Version: 2.0
Name: mcast-tester
Version: 0.2.dev3
Summary: An IP multicast traffic generator.
Home-page: https://github.com/kriswans/ipMCAST_Lab_Tools/tree/master/mcast_tester
Author: Kris Swanson
Author-email: kriswans@cisco.com
License: MIT
Keywords: Multicast,traffic-generator,IP-Multicast
Platform: UNKNOWN
Classifier: Development Status :: 3 - Alpha
Classifier: Intended Audience :: Developers
Classifier: Topic :: Software Development :: Build Tools
Classifier: License :: OSI Approved :: MIT License
Classifier: Programming Language :: Python :: 3.6
Requires-Python: >=3.6
Requires-Dist: ipaddress
